CHANGELOG.md
README.md
sciengdox/__init__.py
sciengdox/compiledoc.py
sciengdox/constants/__init__.py
sciengdox/figures/__init__.py
sciengdox/figures/figures.py
sciengdox/pandoc_pythonexec/__init__.py
sciengdox/pandoc_pythonexec/filter.py
sciengdox/tables/__init__.py
sciengdox/tables/tables.py
sciengdox/tests/__init__.py
sciengdox/tests/test_constants.py
sciengdox/tests/test_figures.py
sciengdox/tests/test_tables.py
sciengdox/tests/units/__init__.py
sciengdox/tests/units/test_checks.py
sciengdox/tests/units/test_conversions.py
sciengdox/tests/units/test_print_quantity.py
sciengdox/units/__init__.py
sciengdox/units/checks.py
sciengdox/units/conversions.py
sciengdox/units/unit_defs.txt
sciengdox-0.11.0.dist-info/entry_points.txt
sciengdox-0.11.0.dist-info/LICENSE
sciengdox-0.11.0.dist-info/METADATA
sciengdox-0.11.0.dist-info/WHEEL
sciengdox-0.11.0.dist-info/RECORD
