Metadata-Version: 2.1
Name: sciengdox
Version: 0.11.0
Summary: Science/engineering dynamic doc generation
Home-page: https://github.com/gbingersoll/sciengdox
License: MIT
Keywords: science,engineering,documentation,scipy,pandoc
Author: Greg Ingersoll
Author-email: greg.ingersoll@convolutionresearch.com
Requires-Python: >=3.9,<4.0
Classifier: Development Status :: 4 - Beta
Classifier: License :: OSI Approved :: MIT License
Classifier: Natural Language :: English
Classifier: Operating System :: OS Independent
Classifier: Programming Language :: Python :: 3
Classifier: Programming Language :: Python :: 3.9
Classifier: Programming Language :: Python :: 3.10
Classifier: Programming Language :: Python :: 3.11
Classifier: Programming Language :: Python :: 3
Classifier: Topic :: Scientific/Engineering
Classifier: Topic :: Text Processing :: Linguistic
Provides-Extra: examples
Requires-Dist: Pint (>=0.18,<0.19)
Requires-Dist: beautifulsoup4 (>=4.10.0,<5.0.0)
Requires-Dist: colorama (>=0.4.4,<0.5.0)
Requires-Dist: kaleido (==0.2.1) ; extra == "examples"
Requires-Dist: matplotlib (>=3.5.1,<4.0.0) ; extra == "examples"
Requires-Dist: numpy (>=1.22.2,<2.0.0)
Requires-Dist: panflute (>=2.1.3,<3.0.0)
Requires-Dist: plotly (>=5.6.0,<6.0.0) ; extra == "examples"
Requires-Dist: pysvglib (>=0.3.2,<0.4.0)
Requires-Dist: scipy (>=1.8.0,<2.0.0)
Project-URL: Repository, https://github.com/gbingersoll/sciengdox
